[
    {
        "Id": "1",
        "PlanName": "FREE",
        "PlanCost": "0",
        "Duration": "30",
        "Description": "Responsive / Mobile Friendly Responsive / Mobile Friendly  Responsive / Mobile Friendly  Responsive / Mobile Friendly<div><br></div>",
        "Isdeleted":false,
        "InsertedBy": "1",
        "InsertedDate": "2020-12-24 12:19:12.324323",
        "UpdatedBy": "1",
        "UpdatedDate": "2021-02-12 07:19:22.721773",
        "DeletedBy": "0",
        "DeletedDate": "2021-03-22 12:13:25.578853"
    },
    {
        "Id": "2",
        "PlanName": "Starter",
        "PlanCost": "399",
        "Duration": "30",
        "Description": "Build Tables, Menus, Orders, Bills and more.",
        "Isdeleted":false,
        "InsertedBy": "1",
        "InsertedDate": "2020-12-24 12:20:05.881911",
        "UpdatedBy": "1",
        "UpdatedDate": "2021-03-22 12:13:25.578853",
        "DeletedBy": "0",
        "DeletedDate": "2021-03-22 12:13:25.578853"
    },
    {
        "Id": "3",
        "PlanName": "Main Course",
        "PlanCost": "599",
        "Duration": "30",
        "Description": "POS, Tables, Bills, Menus, Orders, Reports and more.",
        "Isdeleted":false,
        "InsertedBy": "1",
        "InsertedDate": "2020-12-24 12:20:36.059647",
        "UpdatedBy": "1",
        "UpdatedDate": "2021-03-22 12:14:09.623955",
        "DeletedBy": "0",
        "DeletedDate": "2021-03-22 12:13:25.578853"
    },
    {
        "Id": "4",
        "PlanName": "ULTIMATE",
        "PlanCost": "550000",
        "Duration": "730",
        "Description": "Responsive / Mobile Friendly",
        "Isdeleted":true,
        "InsertedBy": "1",
        "InsertedDate": "2020-12-24 12:21:10.065579",
        "UpdatedBy": "1",
        "UpdatedDate": "2021-02-12 07:17:19.205376",
        "DeletedBy": "1",
        "DeletedDate": "2021-03-22 10:11:02.340802"
    },
    {
        "Id": "5",
        "PlanName": "Gold plan",
        "PlanCost": "5300",
        "Duration": "90",
        "Description": "gghghf",
        "Isdeleted":true,
        "InsertedBy": "1",
        "InsertedDate": "2021-01-26 09:17:42.914601",
        "UpdatedBy": "0",
       "UpdatedDate": "2021-03-22 12:13:25.578853",
        "DeletedBy": "1",
        "DeletedDate": "2021-01-26 11:40:46.162654"
    },
    {
        "Id": "6",
        "PlanName": "Silver",
        "PlanCost": "300",
        "Duration": "10",
        "Description": "gh",
        "Isdeleted":true,
        "InsertedBy": "1",
        "InsertedDate": "2021-01-26 10:03:08.162034",
        "UpdatedBy": "0",
       "UpdatedDate": "2021-03-22 12:13:25.578853",
        "DeletedBy": "1",
        "DeletedDate": "2021-01-26 11:40:35.995626"
    },
    {
        "Id": "7",
        "PlanName": "54645645",
        "PlanCost": "0",
        "Duration": "0",
        "Description": "",
        "Isdeleted":true,
        "InsertedBy": "1",
        "InsertedDate": "2021-01-26 10:10:20.467449",
        "UpdatedBy": "0",
       "UpdatedDate": "2021-03-22 12:13:25.578853",
        "DeletedBy": "1",
        "DeletedDate": "2021-01-26 11:34:13.757339"
    },
    {
        "Id": "8",
        "PlanName": "Gold",
        "PlanCost": "500",
        "Duration": "30",
        "Description": "jhgfjsdh",
        "Isdeleted":true,
        "InsertedBy": "1",
        "InsertedDate": "2021-01-26 12:14:35.395060",
        "UpdatedBy": "0",
       "UpdatedDate": "2021-03-22 12:13:25.578853",
        "DeletedBy": "1",
        "DeletedDate": "2021-01-29 08:17:49.930912"
    },
    {
        "Id": "9",
        "PlanName": "Gold ",
        "PlanCost": "1000",
        "Duration": "80",
        "Description": "fghfhfd",
        "Isdeleted":true,
        "InsertedBy": "1",
        "InsertedDate": "2021-02-09 12:35:47.706787",
        "UpdatedBy": "0",
       "UpdatedDate": "2021-03-22 12:13:25.578853",
        "DeletedBy": "1",
        "DeletedDate": "2021-02-11 12:58:18.344880"
    },
    {
        "Id": "10",
        "PlanName": "Golds",
        "PlanCost": "70",
        "Duration": "4000",
        "Description": "<b>rtytrytr</b><div>yrttttttttttttttty</div><div>rtttttttttttt</div>",
        "Isdeleted":true,
        "InsertedBy": "1",
        "InsertedDate": "2021-02-11 11:58:54.180658",
        "UpdatedBy": "0",
       "UpdatedDate": "2021-03-22 12:13:25.578853",
        "DeletedBy": "1",
        "DeletedDate": "2021-02-11 12:58:22.869082"
    },
    {
        "Id": "11",
        "PlanName": "Silver",
        "PlanCost": "300",
        "Duration": "80",
        "Description": "cccc<div>fgfdgdf</div><div>ghjghj</div><div>ffghfghf</div><div>hgjhg</div><div>hjghjgh</div>",
        "Isdeleted":true,
        "InsertedBy": "1",
        "InsertedDate": "2021-02-11 12:02:44.777370",
        "UpdatedBy": "0",
       "UpdatedDate": "2021-03-22 12:13:25.578853",
        "DeletedBy": "1",
        "DeletedDate": "2021-02-11 12:58:39.351824"
    },
    {
        "Id": "12",
        "PlanName": "plan name",
        "PlanCost": "3000",
        "Duration": "90",
        "Description": "<p><font face=\"Arial\">ghhjg</font></p><p><font face=\"Arial\">ghjgh</font></p><p><font face=\"Arial\">ghj</font></p>",
        "Isdeleted":true,
        "InsertedBy": "1",
        "InsertedDate": "2021-02-12 06:00:07.540358",
        "UpdatedBy": "1",
        "UpdatedDate": "2021-02-12 06:13:36.740352",
        "DeletedBy": "1",
        "DeletedDate": "2021-02-12 06:17:58.280180"
    },
    {
        "Id": "13",
        "PlanName": "Silver",
        "PlanCost": "0",
        "Duration": "0",
        "Description": "dfgfdg<div>kdsgja bbuyyduysay</div><div><br></div>",
        "Isdeleted":true,
        "InsertedBy": "1",
        "InsertedDate": "2021-02-12 06:25:03.736813",
        "UpdatedBy": "1",
        "UpdatedDate": "2021-02-12 07:02:24.490757",
        "DeletedBy": "1",
        "DeletedDate": "2021-02-12 07:59:13.374832"
    },
    {
        "Id": "14",
        "PlanName": "ffgh",
        "PlanCost": "0",
        "Duration": "0",
        "Description": "fgfgh<div>hjghj</div>",
        "Isdeleted":true,
        "InsertedBy": "1",
        "InsertedDate": "2021-02-12 07:57:58.285587",
        "UpdatedBy": "1",
        "UpdatedDate": "2021-02-12 07:59:28.126843",
        "DeletedBy": "1",
        "DeletedDate": "2021-02-12 08:23:11.469738"
    },
    {
        "Id": "15",
        "PlanName": "Gold",
        "PlanCost": "8000",
        "Duration": "70",
        "Description": "<ol><li><font face=\"Roboto, Helvetica Neue, sans-serif\">fghf</font></li><li><font face=\"Roboto, Helvetica Neue, sans-serif\">ghj</font></li><li><font face=\"Roboto, Helvetica Neue, sans-serif\">jhk</font></li></ol>",
        "Isdeleted":true,
        "InsertedBy": "1",
        "InsertedDate": "2021-02-12 08:23:54.451187",
        "UpdatedBy": "1",
        "UpdatedDate": "2021-02-12 10:45:14.856706",
        "DeletedBy": "1",
        "DeletedDate": "2021-02-12 10:49:38.595962"
    }
]